[
  {
    "file": "default-showcase.json",
    "name": "Showcase",
    "game": "Any",
    "author": "LordVicky",
    "description": "Demonstrates multi-zone feedback (L2) and slope (R2).",
    "capabilities": "L2 multi-zone · R2 slope",
    "tier": "verified"
  },
  {
    "file": "nier-replicant.json",
    "name": "Nier Replicant",
    "game": "NieR Replicant",
    "author": "LordVicky",
    "description": "L2 stays soft, then stiffens hard at the end of the pull and rumbles the longer you hold it; R2 is a light weapon click with an early wall.",
    "capabilities": "L2 multi-zone · R2 weapon · 1 modifier",
    "tier": "community"
  },
  {
    "file": "stray.json",
    "name": "Stray",
    "game": "Stray",
    "author": "LordVicky",
    "description": "A gentle L2 ramp that firms up through the pull, and an R2 with a ridge mid-travel that settles into a slow rumble when you hold it.",
    "capabilities": "L2 slope · R2 multi-zone · 1 modifier",
    "tier": "community"
  }
]
